assure/__init__.py
assure/bytes.py
assure/plural.py
assure/stream.py
assure/vector.py
assure-0.0.6.dist-info/METADATA
assure-0.0.6.dist-info/WHEEL
assure-0.0.6.dist-info/top_level.txt
assure-0.0.6.dist-info/RECORD
